EDA PLAYGROUND FILES/design.sv
`timescale 1ns / 1ps

module binary_stream_adder (
    input clk, rst, A, B,   // Declare inputs
    output reg Sum          // Declare output as reg
);
    reg carry;              // Declare carry as reg

    // State Encoding using parameters
    parameter S0 = 1'b0, S1 = 1'b1;
    reg current_state, next_state;

    // Sequential logic: state transitions
    always @(posedge clk or posedge rst) begin
        if (rst) begin
            current_state <= S0;
            carry <= 0;
        end else begin
            current_state <= next_state;
        end
    end

    // Combinational logic: next state and output logic
    always @(*) begin
        case (current_state)
            S0: begin
                Sum = A ^ B;      // Sum output = A XOR B
                carry = A & B;    // Carry = A AND B
                next_state = (A & B) ? S1 : S0;
            end
            S1: begin
                Sum = A ^ B ^ carry; // Sum with carry
                carry = (A & B) | (A & carry) | (B & carry); // Updated Carry
                next_state = (carry) ? S1 : S0;
            end
        endcase
    end
endmodule

EDA PLAYGROUND FILES/testbench.sv
`timescale 1ns / 1ps

module binary_stream_adder_tb;
    reg clk, rst, A, B;
    wire Sum;

    // Instantiate the binary_stream_adder module
    binary_stream_adder uut (
        .clk(clk), 
        .rst(rst), 
        .A(A), 
        .B(B), 
        .Sum(Sum)
    );

    // Clock generation
    always #5 clk = ~clk;

    // Test sequence
    initial begin
        $dumpfile("binary_stream_adder_tb.vcd");  // ✅ Generates waveform for GTKWave
        $dumpvars(0, binary_stream_adder_tb);

        clk = 0; rst = 1; A = 0; B = 0; #10;  // Reset
        rst = 0;

        A = 0; B = 0; #10;
        A = 0; B = 1; #10;
        A = 1; B = 0; #10;
        A = 1; B = 1; #10;

        A = 0; B = 1; #10;
        A = 1; B = 1; #10;

        $display("Simulation Complete");  // ✅ Optional confirmation message
        $finish;
    end
endmodule

EDA PLAYGROUND FILES/binary_stream_adder_tb.vcd
$date
	Tue Apr  1 03:21:18 2025
$end
$version
	Icarus Verilog
$end
$timescale
	1ps
$end
$scope module binary_stream_adder_tb $end
$var wire 1 ! Sum $end
$var reg 1 " A $end
$var reg 1 # B $end
$var reg 1 $ clk $end
$var reg 1 % rst $end
$scope module uut $end
$var wire 1 " A $end
$var wire 1 # B $end
$var wire 1 $ clk $end
$var wire 1 % rst $end
$var parameter 1 & S0 $end
$var parameter 1 ' S1 $end
$var reg 1 ! Sum $end
$var reg 1 ( carry $end
$var reg 1 ) current_state $end
$var reg 1 * next_state $end
$upscope $end
$upscope $end
$enddefinitions $end
$comment Show the parameter values. $end
$dumpall
1'
0&
$end
#0
$dumpvars
0*
0)
0(
1%
0$
0#
0"
0!
$end
#5000
1$
#10000
0$
0%
#15000
1$
#20000
1!
0$
1#
#25000
1$
#30000
0$
0#
1"
#35000
1$
#40000
1*
1(
0!
0$
1#
#45000
1!
1)
1$
#50000
0!
0$
0"
#55000
1$
#60000
1!
0$
1"
